pmmv/__init__.py
pmmv/main.py
pmmv-0.4.0.dist-info/licenses/LICENCE
pmmv-0.4.0.dist-info/METADATA
pmmv-0.4.0.dist-info/WHEEL
pmmv-0.4.0.dist-info/entry_points.txt
pmmv-0.4.0.dist-info/top_level.txt
pmmv-0.4.0.dist-info/RECORD
