Metadata-Version: 2.4
Name: pmmv
Version: 0.4.0
Summary: PMMV - Python Mass Move: A tool for batch renaming/moving files with an interactive editor
Author-email: Akemi Izuko <author@example.com>
License: MIT
Project-URL: Homepage, https://codeberg.org/akemi/pmmv
Project-URL: Repository, https://codeberg.org/akemi/pmmv.git
Classifier: Programming Language :: Python :: 3
Classifier: Programming Language :: Python :: 3.11
Classifier: Programming Language :: Python :: 3.12
Classifier: Programming Language :: Python :: 3.13
Classifier: Programming Language :: Python :: 3.14
Classifier: License :: OSI Approved :: MIT License
Requires-Python: >=3.11
License-File: LICENCE
Dynamic: license-file
